{
    "cardTypes": {
        "Base":          {"width": 1.00, "height": 0.72, "tokens": ["damage", "epicDepleted","abilityDepleted"]},
        "Upgrade":       {"width": 0.72, "height": 1.0, "tokens": []},
        "Unit":          {"width": 0.72, "height": 1.0, "tokens": ["damage"]},
        "Leader":        {"width": 1.00, "height": 0.72, "tokens": ["epicDepleted","abilityDepleted"]},
        "Event":         {"width": 0.72, "height": 1.0, "tokens": []},
        "LeaderUnit":    {"width": 0.72, "height": 1.0, "tokens": ["damage","abilityDepleted"]} 
    }
}
